gc_model_monitoring/__init__.py
gc_model_monitoring/Basic_examples/constraint_suite.py
gc_model_monitoring/Basic_examples/inspect_profile.py
gc_model_monitoring/Basic_examples/loggingdata.py
gc_model_monitoring/Basic_examples/merging_profiles.py
gc_model_monitoring/Basic_examples/schema_configuration.py
gc_model_monitoring/Basic_examples/visualisation.py
gc_model_monitoring/advance_example/condition_count.py
gc_model_monitoring/advance_example/condition_count_emails_mapping.py
gc_model_monitoring/advance_example/condition_count_json_mapper.py
gc_model_monitoring/advance_example/condition_validators.py
gc_model_monitoring/advance_example/customsmet.py
gc_model_monitoring/advance_example/dataconstraint.py
gc_model_monitoring/advance_example/dataconstraint_mapping.py
gc_model_monitoring/advance_example/drift_algo.py
gc_model_monitoring/advance_example/drift_mapper.py
gc_model_monitoring/advance_example/log_rotation_mapper.py
gc_model_monitoring/advance_example/logs_rotation.py
gc_model_monitoring/advance_example/metriccons.py
gc_model_monitoring/advance_example/segmentation.py
gc_model_monitoring/advance_example/tracking.py
gc_model_monitoring/advance_example/v0tov1.py
gc_model_monitoring/data_pipelines/bigquery.py
gc_model_monitoring/data_pipelines/dask_endpoint.py
gc_model_monitoring/data_pipelines/fugue_endpoint.py
gc_model_monitoring/data_pipelines/pyspark_script.py
gc_model_monitoring/data_pipelines/ray_endpoints.py
gc_model_monitoring/experimental/audioexamp.py
gc_model_monitoring/experimental/embedding_distance.py
gc_model_monitoring/experimental/nlpsummarize.py
gc_model_monitoring/experimental/performance.py
gc_model_monitoring/experimental/validators.py
gc_model_monitoring/gencrafter/__init__.py
gc_model_monitoring/gencrafter/api/__init__.py
gc_model_monitoring/gencrafter/api/annotations.py
gc_model_monitoring/gencrafter/api/fugue/__init__.py
gc_model_monitoring/gencrafter/api/fugue/profiler.py
gc_model_monitoring/gencrafter/api/fugue/registry.py
gc_model_monitoring-0.2.1.dist-info/METADATA
gc_model_monitoring-0.2.1.dist-info/WHEEL
gc_model_monitoring-0.2.1.dist-info/top_level.txt
gc_model_monitoring-0.2.1.dist-info/RECORD
