Metadata-Version: 2.4
Name: gc-model-monitoring
Version: 0.2.1
Summary: A lightweight model monitoring library for GenCrafter AI systems
Author-email: GenCrafter <hello@gencrafter.io>
License-Expression: Apache-2.0
Requires-Python: >=3.7
Requires-Dist: fastapi
Requires-Dist: numpy
Requires-Dist: requests
Requires-Dist: uvicorn
Requires-Dist: whylogs_sketching
Requires-Dist: pydantic
Requires-Dist: yfinance
Requires-Dist: pyspark
Requires-Dist: ray
Requires-Dist: pandas
Requires-Dist: pandas_gbq
Requires-Dist: scikit-learn
Requires-Dist: pyAudioAnalysis
Requires-Dist: fugue
Requires-Dist: boto3
Requires-Dist: ipython
Requires-Dist: whylabs-client
Requires-Dist: backoff
Requires-Dist: pillow
